Workbook

Sheet Opportunity Hopper
A1: ID | B1: Aligned to Goal: | C1: Title | D1: Description | E1: Is the process standardised? | F1: Is the data structured and consistent? | G1: Does the process require manual intervention? | H1: Are there frequent exceptions or edge cases? | I1: Does the process rely on multiple system integrations? | J1: Complexity (AUTO) | K1: Time to Complete Process (mins) | L1: Volume (per month) | M1: Time spent per month (min) | N1: Time Spent per month (hrs) | O1: Proposed Solution | P1: Proposed Vendor | Q1: Process Re-engineering Required? | R1: Explanation: | S1: Feasibility | T1: Key Stakeholder Name | U1: Key Stakeholder Email | V1: Date Logged | W1: Date Signed Off | X1: Developed by: Business Analyst
A2: OPP-001 | B2: Make More money | C2: Automate Customer Support FAQs | D2: Deploy a chatbot to handle common customer queries. | E2: Low | F2: Low | G2: Medium | H2: Medium | I2: Low | J2: =IF(COUNTIF(E2:I2, "Low") > COUNTIF(E2:I2, "Medium"), IF(COUNTIF(E2:I2, "Low") > COUNTIF(E2:I2, "High"), "Low", IF(COUNTIF(E2:I2, "Low") = COUNTIF(E2:I2, "High"), "Medium", "High") ), IF(COUNTIF(E2:I2, "Medium") >= COUNTIF(E2:I2, "High"), "Medium", "High" ) ) -> Low | K2: =8*60 -> 480 | L2: 1000 | M2: =L2*K2 -> 480000 | N2: =M2/60 -> 8000 | O2: Automation | P2: Microsoft | Q2: Yes | S2: High | T2: <Name> | U2: <Email> | V2: <Last Week> | W2: <Today> | X2: <Name>
A3: OPP-002 | B3: Stop spending so much | C3: Invoice Processing Automation | D3: Automate invoice data entry and validation. | E3: Medium | F3: Medium | G3: Low | H3: Low | I3: Low | J3: =IF(COUNTIF(E3:I3, "Low") > COUNTIF(E3:I3, "Medium"), IF(COUNTIF(E3:I3, "Low") > COUNTIF(E3:I3, "High"), "Low", IF(COUNTIF(E3:I3, "Low") = COUNTIF(E3:I3, "High"), "Medium", "High") ), IF(COUNTIF(E3:I3, "Medium") >= COUNTIF(E3:I3, "High"), "Medium", "High" ) ) -> Low | K3: 120 | L3: 500 | M3: =L3*K3 -> 60000 | N3: =M3/60 -> 1000 | O3: Automation | P3: BluePrism | Q3: No | S3: Medium | T3: <Name> | U3: <Email> | V3: <Last Week> | W3: <Today> | X3: <Name>
A4: OPP-003 | B4: Grow in market | C4: Employee Onboarding Chatbot | D4: Create a chatbot to guide employees through onboarding. | E4: Low | F4: Low | G4: Low | H4: Low | I4: Low | J4: =IF(COUNTIF(E4:I4, "Low") > COUNTIF(E4:I4, "Medium"), IF(COUNTIF(E4:I4, "Low") > COUNTIF(E4:I4, "High"), "Low", IF(COUNTIF(E4:I4, "Low") = COUNTIF(E4:I4, "High"), "Medium", "High") ), IF(COUNTIF(E4:I4, "Medium") >= COUNTIF(E4:I4, "High"), "Medium", "High" ) ) -> Low | K4: =3*60 -> 180 | L4: 50 | M4: =L4*K4 -> 9000 | N4: =M4/60 -> 150 | O4: Chatbot | P4: Voiceflow | Q4: Yes | S4: High | T4: <Name> | U4: <Email> | V4: <Last Week> | W4: <Today> | X4: <Name>
A5: OPP-004 | B5: Improve processing times | C5: Order Status Updates Chatbot | D5: Automate customer order status inquiries via chatbot. | E5: Low | F5: Medium | G5: High | H5: Low | I5: Low | J5: =IF(COUNTIF(E5:I5, "Low") > COUNTIF(E5:I5, "Medium"), IF(COUNTIF(E5:I5, "Low") > COUNTIF(E5:I5, "High"), "Low", IF(COUNTIF(E5:I5, "Low") = COUNTIF(E5:I5, "High"), "Medium", "High") ), IF(COUNTIF(E5:I5, "Medium") >= COUNTIF(E5:I5, "High"), "Medium", "High" ) ) -> Low | K5: 5 | L5: 2000 | M5: =L5*K5 -> 10000 | N5: =M5/60 -> 166.66667 | O5: AI | P5: Celonis | Q5: No | S5: High | T5: <Name> | U5: <Email> | V5: <Last Week> | W5: <Today> | X5: <Name>
A6: OPP-005 | B6: Enabling scaling | C6: Inventory Replenishment RPA | D6: Implement RPA for automated inventory restocking. | E6: Medium | F6: Medium | G6: Medium | H6: Medium | I6: Medium | J6: =IF(COUNTIF(E6:I6, "Low") > COUNTIF(E6:I6, "Medium"), IF(COUNTIF(E6:I6, "Low") > COUNTIF(E6:I6, "High"), "Low", IF(COUNTIF(E6:I6, "Low") = COUNTIF(E6:I6, "High"), "Medium", "High") ), IF(COUNTIF(E6:I6, "Medium") >= COUNTIF(E6:I6, "High"), "Medium", "High" ) ) -> Medium | K6: 20 | L6: 300 | M6: =L6*K6 -> 6000 | N6: =M6/60 -> 100 | O6: Automation | P6: Make.com | Q6: Yes | S6: Medium | T6: <Name> | U6: <Email> | V6: <Last Week> | W6: <Today> | X6: <Name>
A7: OPP-006 | B7: Example | C7: IT Support Ticket Categorisation | D7: Automate categorisation of incoming IT support tickets. | E7: Low | F7: Low | G7: Low | H7: Low | I7: Low | J7: =IF(COUNTIF(E7:I7, "Low") > COUNTIF(E7:I7, "Medium"), IF(COUNTIF(E7:I7, "Low") > COUNTIF(E7:I7, "High"), "Low", IF(COUNTIF(E7:I7, "Low") = COUNTIF(E7:I7, "High"), "Medium", "High") ), IF(COUNTIF(E7:I7, "Medium") >= COUNTIF(E7:I7, "High"), "Medium", "High" ) ) -> Low | K7: 50 | L7: 1500 | M7: =L7*K7 -> 75000 | N7: =M7/60 -> 1250 | O7: Automation | P7: n8n | Q7: Yes | S7: High | T7: <Name> | U7: <Email> | V7: <Last Week> | W7: <Today> | X7: <Name>
A8: OPP-007 | B8: Example | C8: Sales Lead Qualification Bot | D8: Deploy an AI bot to qualify sales leads automatically. | E8: High | F8: High | G8: High | H8: High | I8: High | J8: =IF(COUNTIF(E8:I8, "Low") > COUNTIF(E8:I8, "Medium"), IF(COUNTIF(E8:I8, "Low") > COUNTIF(E8:I8, "High"), "Low", IF(COUNTIF(E8:I8, "Low") = COUNTIF(E8:I8, "High"), "Medium", "High") ), IF(COUNTIF(E8:I8, "Medium") >= COUNTIF(E8:I8, "High"), "Medium", "High" ) ) -> High | K8: 30 | L8: 400 | M8: =L8*K8 -> 12000 | N8: =M8/60 -> 200 | O8: AI | P8: OpenAI | Q8: No | S8: Medium | T8: <Name> | U8: <Email> | V8: <Last Week> | W8: <Today> | X8: <Name>
A9: OPP-008 | B9: Example | C9: Marketing Campaign Automation | D9: Automate creation and scheduling of marketing campaigns. | E9: Low | F9: Low | G9: Low | H9: Low | I9: Low | J9: =IF(COUNTIF(E9:I9, "Low") > COUNTIF(E9:I9, "Medium"), IF(COUNTIF(E9:I9, "Low") > COUNTIF(E9:I9, "High"), "Low", IF(COUNTIF(E9:I9, "Low") = COUNTIF(E9:I9, "High"), "Medium", "High") ), IF(COUNTIF(E9:I9, "Medium") >= COUNTIF(E9:I9, "High"), "Medium", "High" ) ) -> Low | K9: 40 | L9: 200 | M9: =L9*K9 -> 8000 | N9: =M9/60 -> 133.33333 | O9: AI | P9: Claude | Q9: No | S9: Medium | T9: <Name> | U9: <Email> | V9: <Last Week> | W9: <Today> | X9: <Name>
A10: OPP-009 | B10: Example | C10: Expense Approval Workflow | D10: Automate approval workflows for expense claims. | E10: Low | F10: Low | G10: Medium | H10: High | I10: Low | J10: =IF(COUNTIF(E10:I10, "Low") > COUNTIF(E10:I10, "Medium"), IF(COUNTIF(E10:I10, "Low") > COUNTIF(E10:I10, "High"), "Low", IF(COUNTIF(E10:I10, "Low") = COUNTIF(E10:I10, "High"), "Medium", "High") ), IF(COUNTIF(E10:I10, "Medium") >= COUNTIF(E10:I10, "High"), "Medium", "High" ) ) -> Low | K10: =60*6 -> 360 | L10: 600 | M10: =L10*K10 -> 216000 | N10: =M10/60 -> 3600 | O10: Chatbot | P10: Example | Q10: No | S10: Medium | T10: <Name> | U10: <Email> | V10: <Last Week> | W10: <Today> | X10: <Name>
A11: OPP-010 | B11: Example | C11: Appointment Scheduling AI | D11: AI-powered scheduling assistant for appointments. | E11: Low | F11: Low | G11: Low | H11: Low | I11: Low | J11: =IF(COUNTIF(E11:I11, "Low") > COUNTIF(E11:I11, "Medium"), IF(COUNTIF(E11:I11, "Low") > COUNTIF(E11:I11, "High"), "Low", IF(COUNTIF(E11:I11, "Low") = COUNTIF(E11:I11, "High"), "Medium", "High") ), IF(COUNTIF(E11:I11, "Medium") >= COUNTIF(E11:I11, "High"), "Medium", "High" ) ) -> Low | K11: =10*8*60 -> 4800 | L11: 1000 | M11: =L11*K11 -> 4800000 | N11: =M11/60 -> 80000 | O11: Chatbot | P11: Example | Q11: No | S11: High | T11: <Name> | U11: <Email> | V11: <Last Week> | W11: <Today> | X11: <Name>

Sheet Business Case - Fundamentals
B3: Business Case Details
B5: Number of working days in a year | C5: 261 | D5: <- Update
B6: Holiday | C6: 25 | D6: <- Update
B7: Working days per FTE | C7: =C5-C6 -> 236 | D7: <- Fixed
B8: Hours worked per shift | C8: 8 | D8: <- Update
B9: Total Hours at work | C9: =C8*C7 -> 1888 | D9: <- Fixed
B11: Efficiency | C11: 0.72 | D11: <- Update
B12: Total hours worked | C12: =C9*C11 -> 1359.36 | D12: <- Fixed
B15: Total Number of FTE | C15: =SUM(C19+G19+K19) -> 75 | D15: <- Fixed
B16: Total Spend on FTE | C16: =C21+G21+K21 -> 3975000 | D16: <- Fixed
B18: Business Area 1 (e.g HR) | F18: Business Area 2 (e.g. Customer Service) | J18: Business Area 3 (e.g. Finance)
B19: Number of FTE | C19: 30 | D19: <- Update | F19: Number of FTE | G19: 30 | H19: <- Update | J19: Number of FTE | K19: 15 | L19: <- Update
B20: Cost per FTE | C20: 35000 | D20: <- Update | F20: Cost per FTE | G20: 70000 | H20: <- Update | J20: Cost per FTE | K20: 55000 | L20: <- Update
B21: Total Cost of FTEs | C21: =C20*C19 -> 1050000 | D21: <- Fixed | F21: Total Cost of FTEs | G21: =G20*G19 -> 2100000 | H21: <- Fixed | J21: Total Cost of FTEs | K21: =K20*K19 -> 825000 | L21: <- Fixed
B23: Cost Per Hour | C23: =C20/$C$12 -> 25.747411 | D23: <- Fixed | F23: Cost Per Hour | G23: =G20/$C$12 -> 51.494821 | H23: <- Fixed | J23: Cost Per Hour | K23: =K20/$C$12 -> 40.460217 | L23: <- Fixed
B24: Cost Per Min | C24: =C23/60 -> 0.42912351 | D24: <- Fixed | F24: Cost Per Min | G24: =G23/60 -> 0.85824702 | H24: <- Fixed | J24: Cost Per Min | K24: =K23/60 -> 0.67433694 | L24: <- Fixed

Sheet Business Case
A1: ID | B1: Aligned to Goal: | C1: Title | D1: Description | E1: Complexity (AUTO) | F1: Time to Complete Process (mins) | G1: Volume (per month) | H1: Time spent per month (min) | I1: Time Spent per month (hrs) | J1: Proposed Solution | K1: Process Re-engineering Required? | L1: Feasibility | M1: Business Case -> | N1: Reduction in cases? (%) | O1: New Total Monthly Case Total | P1: Estimated Time Saving per case (%) | Q1: New Time Per case (Min) | R1: Associated Business Team | S1: Cases Saved Annually | T1: Time Saved Annually (Min) | U1: Time Saved Annually (Hrs) | V1: FTE Saved | W1: Cost Saved
A2: OPP-010 | B2: =VLOOKUP(A2,Table1[],2) -> Example | C2: =VLOOKUP(A2,Table1[],3) -> Appointment Scheduling AI | D2: =VLOOKUP(A2,Table1[],4) -> AI-powered scheduling assistant for appointments. | E2: =VLOOKUP(A2,Table1[],10) -> Low | F2: =VLOOKUP(A2,Table1[],11) -> 4800 | G2: =VLOOKUP(A2,Table1[],12) -> 1000 | H2: =VLOOKUP(A2,Table1[],13) -> 4800000 | I2: =VLOOKUP(A2,Table1[],14) -> 80000 | J2: =VLOOKUP(A2,Table1[],15) -> Chatbot | K2: =VLOOKUP(A2,Table1[],17) -> No | L2: =VLOOKUP(A2,Table1[],19) -> High | N2: 0.2 | O2: =(1-N2)*G2 -> 800 | P2: 0.03 | Q2: =(1-P2)*F2 -> 4656 | R2: Business Team 2 | S2: =(G2-O2)*12 -> 2400 | T2: =(F2-Q2)*(O2*12) -> 1382400 | U2: =T2/60 -> 23040 | V2: =U2/'Business Case - Fundamentals'!$C$12 -> 16.949153 | W2: =IF(R2="Business Team 1", 'Business Case - Fundamentals'!$C$20 * V2, IF(R2="Business Team 2", 'Business Case - Fundamentals'!$G$20 * V2, IF(R2="Business Team 3", 'Business Case - Fundamentals'!$K$20 * V2, "No Match"))) -> 1186440.7
A3: OPP-001 | B3: =VLOOKUP(A3,Table1[],2) -> Make More money | C3: =VLOOKUP(A3,Table1[],3) -> Automate Customer Support FAQs | D3: =VLOOKUP(A3,Table1[],4) -> Deploy a chatbot to handle common customer queries. | E3: =VLOOKUP(A3,Table1[],10) -> Low | F3: =VLOOKUP(A3,Table1[],11) -> 480 | G3: =VLOOKUP(A3,Table1[],12) -> 1000 | H3: =VLOOKUP(A3,Table1[],13) -> 480000 | I3: =VLOOKUP(A3,Table1[],14) -> 8000 | J3: =VLOOKUP(A3,Table1[],15) -> Automation | K3: =VLOOKUP(A3,Table1[],17) -> Yes | L3: =VLOOKUP(A3,Table1[],19) -> High | N3: 0.5 | O3: =(1-N3)*G3 -> 500 | P3: 0.2 | Q3: =(1-P3)*F3 -> 384 | R3: Business Team 2 | S3: =(G3-O3)*12 -> 6000 | T3: =(F3-Q3)*(O3*12) -> 576000 | U3: =T3/60 -> 9600 | V3: =U3/'Business Case - Fundamentals'!$C$12 -> 7.0621469 | W3: =IF(R3="Business Team 1", 'Business Case - Fundamentals'!$C$20 * V3, IF(R3="Business Team 2", 'Business Case - Fundamentals'!$G$20 * V3, IF(R3="Business Team 3", 'Business Case - Fundamentals'!$K$20 * V3, "No Match"))) -> 494350.28
A4: OPP-009 | B4: =VLOOKUP(A4,Table1[],2) -> Example | C4: =VLOOKUP(A4,Table1[],3) -> Expense Approval Workflow | D4: =VLOOKUP(A4,Table1[],4) -> Automate approval workflows for expense claims. | E4: =VLOOKUP(A4,Table1[],10) -> Low | F4: =VLOOKUP(A4,Table1[],11) -> 360 | G4: =VLOOKUP(A4,Table1[],12) -> 600 | H4: =VLOOKUP(A4,Table1[],13) -> 216000 | I4: =VLOOKUP(A4,Table1[],14) -> 3600 | J4: =VLOOKUP(A4,Table1[],15) -> Chatbot | K4: =VLOOKUP(A4,Table1[],17) -> No | L4: =VLOOKUP(A4,Table1[],19) -> Medium | N4: 0.15 | O4: =(1-N4)*G4 -> 510 | P4: 0.1 | Q4: =(1-P4)*F4 -> 324 | R4: Business Team 2 | S4: =(G4-O4)*12 -> 1080 | T4: =(F4-Q4)*(O4*12) -> 220320 | U4: =T4/60 -> 3672 | V4: =U4/'Business Case - Fundamentals'!$C$12 -> 2.7012712 | W4: =IF(R4="Business Team 1", 'Business Case - Fundamentals'!$C$20 * V4, IF(R4="Business Team 2", 'Business Case - Fundamentals'!$G$20 * V4, IF(R4="Business Team 3", 'Business Case - Fundamentals'!$K$20 * V4, "No Match"))) -> 189088.98
A5: OPP-006 | B5: =VLOOKUP(A5,Table1[],2) -> Example | C5: =VLOOKUP(A5,Table1[],3) -> IT Support Ticket Categorisation | D5: =VLOOKUP(A5,Table1[],4) -> Automate categorisation of incoming IT support tickets. | E5: =VLOOKUP(A5,Table1[],10) -> Low | F5: =VLOOKUP(A5,Table1[],11) -> 50 | G5: =VLOOKUP(A5,Table1[],12) -> 1500 | H5: =VLOOKUP(A5,Table1[],13) -> 75000 | I5: =VLOOKUP(A5,Table1[],14) -> 1250 | J5: =VLOOKUP(A5,Table1[],15) -> Automation | K5: =VLOOKUP(A5,Table1[],17) -> Yes | L5: =VLOOKUP(A5,Table1[],19) -> High | N5: 0.8 | O5: =(1-N5)*G5 -> 300 | P5: 0.7 | Q5: =(1-P5)*F5 -> 15 | R5: Business Team 2 | S5: =(G5-O5)*12 -> 14400 | T5: =(F5-Q5)*(O5*12) -> 126000 | U5: =T5/60 -> 2100 | V5: =U5/'Business Case - Fundamentals'!$C$12 -> 1.5448446 | W5: =IF(R5="Business Team 1", 'Business Case - Fundamentals'!$C$20 * V5, IF(R5="Business Team 2", 'Business Case - Fundamentals'!$G$20 * V5, IF(R5="Business Team 3", 'Business Case - Fundamentals'!$K$20 * V5, "No Match"))) -> 108139.12
A6: OPP-008 | B6: =VLOOKUP(A6,Table1[],2) -> Example | C6: =VLOOKUP(A6,Table1[],3) -> Marketing Campaign Automation | D6: =VLOOKUP(A6,Table1[],4) -> Automate creation and scheduling of marketing campaigns. | E6: =VLOOKUP(A6,Table1[],10) -> Low | F6: =VLOOKUP(A6,Table1[],11) -> 40 | G6: =VLOOKUP(A6,Table1[],12) -> 200 | H6: =VLOOKUP(A6,Table1[],13) -> 8000 | I6: =VLOOKUP(A6,Table1[],14) -> 133.33333 | J6: =VLOOKUP(A6,Table1[],15) -> AI | K6: =VLOOKUP(A6,Table1[],17) -> No | L6: =VLOOKUP(A6,Table1[],19) -> Medium | N6: 0.05 | O6: =(1-N6)*G6 -> 190 | P6: 0.55 | Q6: =(1-P6)*F6 -> 18 | R6: Business Team 3 | S6: =(G6-O6)*12 -> 120 | T6: =(F6-Q6)*(O6*12) -> 50160 | U6: =T6/60 -> 836 | V6: =U6/'Business Case - Fundamentals'!$C$12 -> 0.61499529 | W6: =IF(R6="Business Team 1", 'Business Case - Fundamentals'!$C$20 * V6, IF(R6="Business Team 2", 'Business Case - Fundamentals'!$G$20 * V6, IF(R6="Business Team 3", 'Business Case - Fundamentals'!$K$20 * V6, "No Match"))) -> 33824.741
A7: OPP-002 | B7: =VLOOKUP(A7,Table1[],2) -> Stop spending so much | C7: =VLOOKUP(A7,Table1[],3) -> Invoice Processing Automation | D7: =VLOOKUP(A7,Table1[],4) -> Automate invoice data entry and validation. | E7: =VLOOKUP(A7,Table1[],10) -> Low | F7: =VLOOKUP(A7,Table1[],11) -> 120 | G7: =VLOOKUP(A7,Table1[],12) -> 500 | H7: =VLOOKUP(A7,Table1[],13) -> 60000 | I7: =VLOOKUP(A7,Table1[],14) -> 1000 | J7: =VLOOKUP(A7,Table1[],15) -> Automation | K7: =VLOOKUP(A7,Table1[],17) -> No | L7: =VLOOKUP(A7,Table1[],19) -> Medium | N7: 0.2 | O7: =(1-N7)*G7 -> 400 | P7: 0.1 | Q7: =(1-P7)*F7 -> 108 | R7: Business Team 1 | S7: =(G7-O7)*12 -> 1200 | T7: =(F7-Q7)*(O7*12) -> 57600 | U7: =T7/60 -> 960 | V7: =U7/'Business Case - Fundamentals'!$C$12 -> 0.70621469 | W7: =IF(R7="Business Team 1", 'Business Case - Fundamentals'!$C$20 * V7, IF(R7="Business Team 2", 'Business Case - Fundamentals'!$G$20 * V7, IF(R7="Business Team 3", 'Business Case - Fundamentals'!$K$20 * V7, "No Match"))) -> 24717.514
A8: OPP-007 | B8: =VLOOKUP(A8,Table1[],2) -> Example | C8: =VLOOKUP(A8,Table1[],3) -> Sales Lead Qualification Bot | D8: =VLOOKUP(A8,Table1[],4) -> Deploy an AI bot to qualify sales leads automatically. | E8: =VLOOKUP(A8,Table1[],10) -> High | F8: =VLOOKUP(A8,Table1[],11) -> 30 | G8: =VLOOKUP(A8,Table1[],12) -> 400 | H8: =VLOOKUP(A8,Table1[],13) -> 12000 | I8: =VLOOKUP(A8,Table1[],14) -> 200 | J8: =VLOOKUP(A8,Table1[],15) -> AI | K8: =VLOOKUP(A8,Table1[],17) -> No | L8: =VLOOKUP(A8,Table1[],19) -> Medium | N8: 0.1 | O8: =(1-N8)*G8 -> 360 | P8: 0.25 | Q8: =(1-P8)*F8 -> 22.5 | R8: Business Team 1 | S8: =(G8-O8)*12 -> 480 | T8: =(F8-Q8)*(O8*12) -> 32400 | U8: =T8/60 -> 540 | V8: =U8/'Business Case - Fundamentals'!$C$12 -> 0.39724576 | W8: =IF(R8="Business Team 1", 'Business Case - Fundamentals'!$C$20 * V8, IF(R8="Business Team 2", 'Business Case - Fundamentals'!$G$20 * V8, IF(R8="Business Team 3", 'Business Case - Fundamentals'!$K$20 * V8, "No Match"))) -> 13903.602
A9: OPP-005 | B9: =VLOOKUP(A9,Table1[],2) -> Enabling scaling | C9: =VLOOKUP(A9,Table1[],3) -> Inventory Replenishment RPA | D9: =VLOOKUP(A9,Table1[],4) -> Implement RPA for automated inventory restocking. | E9: =VLOOKUP(A9,Table1[],10) -> Medium | F9: =VLOOKUP(A9,Table1[],11) -> 20 | G9: =VLOOKUP(A9,Table1[],12) -> 300 | H9: =VLOOKUP(A9,Table1[],13) -> 6000 | I9: =VLOOKUP(A9,Table1[],14) -> 100 | J9: =VLOOKUP(A9,Table1[],15) -> Automation | K9: =VLOOKUP(A9,Table1[],17) -> Yes | L9: =VLOOKUP(A9,Table1[],19) -> Medium | N9: 0.6 | O9: =(1-N9)*G9 -> 120 | P9: 0.6 | Q9: =(1-P9)*F9 -> 8 | R9: Business Team 1 | S9: =(G9-O9)*12 -> 2160 | T9: =(F9-Q9)*(O9*12) -> 17280 | U9: =T9/60 -> 288 | V9: =U9/'Business Case - Fundamentals'!$C$12 -> 0.21186441 | W9: =IF(R9="Business Team 1", 'Business Case - Fundamentals'!$C$20 * V9, IF(R9="Business Team 2", 'Business Case - Fundamentals'!$G$20 * V9, IF(R9="Business Team 3", 'Business Case - Fundamentals'!$K$20 * V9, "No Match"))) -> 7415.2542
A10: OPP-003 | B10: =VLOOKUP(A10,Table1[],2) -> Grow in market | C10: =VLOOKUP(A10,Table1[],3) -> Employee Onboarding Chatbot | D10: =VLOOKUP(A10,Table1[],4) -> Create a chatbot to guide employees through onboarding. | E10: =VLOOKUP(A10,Table1[],10) -> Low | F10: =VLOOKUP(A10,Table1[],11) -> 180 | G10: =VLOOKUP(A10,Table1[],12) -> 50 | H10: =VLOOKUP(A10,Table1[],13) -> 9000 | I10: =VLOOKUP(A10,Table1[],14) -> 150 | J10: =VLOOKUP(A10,Table1[],15) -> Chatbot | K10: =VLOOKUP(A10,Table1[],17) -> Yes | L10: =VLOOKUP(A10,Table1[],19) -> High | N10: 0.1 | O10: =(1-N10)*G10 -> 45 | P10: 0.05 | Q10: =(1-P10)*F10 -> 171 | R10: Business Team 3 | S10: =(G10-O10)*12 -> 60 | T10: =(F10-Q10)*(O10*12) -> 4860 | U10: =T10/60 -> 81 | V10: =U10/'Business Case - Fundamentals'!$C$12 -> 0.059586864 | W10: =IF(R10="Business Team 1", 'Business Case - Fundamentals'!$C$20 * V10, IF(R10="Business Team 2", 'Business Case - Fundamentals'!$G$20 * V10, IF(R10="Business Team 3", 'Business Case - Fundamentals'!$K$20 * V10, "No Match"))) -> 3277.2775
A11: OPP-004 | B11: =VLOOKUP(A11,Table1[],2) -> Improve processing times | C11: =VLOOKUP(A11,Table1[],3) -> Order Status Updates Chatbot | D11: =VLOOKUP(A11,Table1[],4) -> Automate customer order status inquiries via chatbot. | E11: =VLOOKUP(A11,Table1[],10) -> Low | F11: =VLOOKUP(A11,Table1[],11) -> 5 | G11: =VLOOKUP(A11,Table1[],12) -> 2000 | H11: =VLOOKUP(A11,Table1[],13) -> 10000 | I11: =VLOOKUP(A11,Table1[],14) -> 166.66667 | J11: =VLOOKUP(A11,Table1[],15) -> AI | K11: =VLOOKUP(A11,Table1[],17) -> No | L11: =VLOOKUP(A11,Table1[],19) -> High | N11: 0.3 | O11: =(1-N11)*G11 -> 1400 | P11: 0.02 | Q11: =(1-P11)*F11 -> 4.9 | R11: Business Team 2 | S11: =(G11-O11)*12 -> 7200 | T11: =(F11-Q11)*(O11*12) -> 1680 | U11: =T11/60 -> 28 | V11: =U11/'Business Case - Fundamentals'!$C$12 -> 0.020597928 | W11: =IF(R11="Business Team 1", 'Business Case - Fundamentals'!$C$20 * V11, IF(R11="Business Team 2", 'Business Case - Fundamentals'!$G$20 * V11, IF(R11="Business Team 3", 'Business Case - Fundamentals'!$K$20 * V11, "No Match"))) -> 1441.855

Sheet Business Case Dashboard
B2: Number of Opportunities Identified | E2: FTE Saved | H2: Cost Saved | K2: Avg. % reduction in cases | N2: Avg. % reduction in time per case cases
B3: =IFERROR(__xludf.DUMMYFUNCTION("COUNTUNIQUE(Business_Case[ID])"),10.0) -> 10 | E3: =IFERROR(__xludf.DUMMYFUNCTION("SUM(FILTER('Business Case'!V2:V11, ('Business Case'!V2:V11<>0) * ('Business Case'!V2:V11<>""N/A""))) "),30.26792019774011) -> 30.26792 | H3: =IFERROR(__xludf.DUMMYFUNCTION("SUM(FILTER('Business Case'!W1:W11, ('Business Case'!W1:W11<>0) * ('Business Case'!W1:W11<>""N/A""))) "),2062599.311440678) -> 2062599.3 | K3: =IFERROR(__xludf.DUMMYFUNCTION("AVERAGE(FILTER('Business Case'!P2:P11, ('Business Case'!P2:P11<>0) * ('Business Case'!P2:P11<>""N/A""))) "),0.26) -> 0.26 | N3: =IFERROR(__xludf.DUMMYFUNCTION("AVERAGE(FILTER('Business Case'!N2:N11, ('Business Case'!N2:N11<>0) * ('Business Case'!N2:N11<>""N/A""))) "),0.3) -> 0.3
B47: Additional Details
B49: Savings by Team
B50: Number of Solutions for Business Team 1 | E50: Number of Solutions for Business Team 2 | H50: Number of Solutions for Business Team 3
B51: =COUNTIF('Business Case'!R2:R11, "Business Team 1") -> 3 | E51: =COUNTIF('Business Case'!R2:R11, "Business Team 2") -> 5 | H51: =COUNTIF('Business Case'!R2:R11, "Business Team 3") -> 2
B58: ^^ Total Value ^^ | E58: ^^ Total Value ^^ | H58: ^^ Total Value ^^
B59: =SUMIFS('Business Case'!W2:W11, 'Business Case'!R2:R11, "Business Team 1") -> 46036.37 | E59: =SUMIFS('Business Case'!W2:W11, 'Business Case'!R2:R11, "Business Team 2") -> 1979460.9 | H59: =SUMIFS('Business Case'!W2:W11, 'Business Case'!R2:R11, "Business Team 3") -> 37102.019
B67: Complexity:
B68: Number of Low Complexity Solutions | E68: Number of Medium Complexity Solutions | H68: Number of High Complexity Solutions
B69: =COUNTIF('Business Case'!E2:E11, "Low") -> 8 | E69: =COUNTIF('Business Case'!E2:E11, "Medium") -> 1 | H69: =COUNTIF('Business Case'!E2:E11, "High") -> 1
B76: ^^ Total Value ^^ | E76: ^^ Total Value ^^ | H76: ^^ Total Value ^^
B77: =SUMIFS('Business Case'!W2:W11, 'Business Case'!E2:E11, "Low") -> 2041280.5 | E77: =SUMIFS('Business Case'!W2:W11, 'Business Case'!E2:E11, "Medium") -> 7415.2542 | H77: =SUMIFS('Business Case'!W2:W11, 'Business Case'!E2:E11, "High") -> 13903.602
B85: Solution Type
B86: Number of AI Solutions | E86: Number of Automation Solutions | H86: Number of Chatbot Solutions
B87: =COUNTIF('Business Case'!J2:J11, "AI") -> 3 | E87: =COUNTIF('Business Case'!J2:J11, "Automation") -> 4 | H87: =COUNTIF('Business Case'!J2:J11, "Chatbot") -> 3
B94: ^^ Total Value ^^ | E94: ^^ Total Value ^^ | H94: ^^ Total Value ^^
B95: =SUMIFS('Business Case'!W2:W11, 'Business Case'!J2:J11, "AI") -> 49170.198 | E95: =SUMIFS('Business Case'!W2:W11, 'Business Case'!J2:J11, "Chatbot") -> 1378806.9 | H95: =SUMIFS('Business Case'!W2:W11, 'Business Case'!J2:J11, "Automation") -> 634622.18
B103: Fesibility
B104: Number of Low Fesibility Solutions | E104: Number of Medium Fesibility Solutions | H104: Number of High Fesibility Solutions
B105: =COUNTIF('Business Case'!L2:L11, "Low") -> 0 | E105: =COUNTIF('Business Case'!L2:L11, "Medium") -> 5 | H105: =COUNTIF('Business Case'!L2:L11, "High") -> 5
B112: ^^ Total Value ^^ | E112: ^^ Total Value ^^ | H112: ^^ Total Value ^^
B113: =SUMIFS('Business Case'!W2:W11, 'Business Case'!L2:L11, "Low") -> 0 | E113: =SUMIFS('Business Case'!W2:W11, 'Business Case'!L2:L11, "Medium") -> 268950.09 | H113: =SUMIFS('Business Case'!W2:W11, 'Business Case'!L2:L11, "High") -> 1793649.2
B121: Process Re-Engineering Required
B122: Process Re-Engineering Required
B123: =COUNTIF('Business Case'!K2:K11, "Yes") -> 4
